{
    "S_pib": 11.2,
    "theta_pib_ModelO": 1.0,
    "theta_pib_ModelA": 0.0,
    "theta_pib_ModelF": 0.0,
    "S_ics": 6.5,
    "theta_ics_ModelO": 1.0,
    "theta_ics_ModelA": 0.0,
    "theta_ics_ModelF": 0.0,
    "S_bub": 1.4,
    "S_iso": 0.4,
    "S_psc": 2.7,
    "S_gce": 0.6,
    "f_bulge_poiss": 0.2,
    "theta_poiss_mcdermott2022": 1.0,
    "theta_poiss_mcdermott2022_bbp": 0.0,
    "theta_poiss_mcdermott2022_x": 0.0,
    "theta_poiss_macias2019": 0.0,
    "theta_poiss_coleman2019": 0.0,
    "gamma_poiss": 1.0,
    "Sps_gce": 1.0,
    "n1_gce": 5.0,
    "n2_gce": 1.0,
    "n3_gce": -5.5,
    "sb1_gce": 10.0,
    "lambdas_gce": 0.4,
    "f_bulge_ps": 0.8,
    "theta_ps_mcdermott2022": 1.0,
    "theta_ps_mcdermott2022_bbp": 0.0,
    "theta_ps_mcdermott2022_x": 0.0,
    "theta_ps_macias2019": 0.0,
    "theta_ps_coleman2019": 0.0,
    "gamma_ps": 1.2,
    "Sps_dsk": 0.3,
    "zs": 0.6,
    "C": 6.0,
    "n1_dsk": 5.0,
    "n2_dsk": 1.0,
    "n3_dsk": -5.5,
    "sb1_dsk": 15.0,
    "lambdas_dsk": 0.7
}